pyconvox/__init__.py
pyconvox/__main__.py
pyconvox/__version__.py
pyconvox-0.2.3.dist-info/LICENSE
pyconvox-0.2.3.dist-info/METADATA
pyconvox-0.2.3.dist-info/WHEEL
pyconvox-0.2.3.dist-info/entry_points.txt
pyconvox-0.2.3.dist-info/top_level.txt
pyconvox-0.2.3.dist-info/RECORD
